wthisj/__init__.py
wthisj/punchingshearsection.py
wthisj-0.2.1.dist-info/METADATA
wthisj-0.2.1.dist-info/WHEEL
wthisj-0.2.1.dist-info/licenses/LICENSE
wthisj-0.2.1.dist-info/RECORD
